{
  "updated_at": "2019-07-27T10:33+0000",
  "event_types": [
    {
      "conference": "DEFCON27",
      "name": "Workshop",
      "id": 40001,
      "color": "#9a3290",
      "updated_at": "2019-07-27T10:33+0000"
    },
    {
      "conference": "DEFCON27",
      "name": "Official Talk",
      "id": 40002,
      "color": "#5c74ff",
      "updated_at": "2019-07-27T10:33+0000"
    },
    {
      "conference": "DEFCON27",
      "name": "Contest",
      "id": 40003,
      "color": "#42d2bc",
      "updated_at": "2019-07-27T10:33+0000"
    },
    {
      "conference": "DEFCON27",
      "name": "Party",
      "id": 40004,
      "color": "#5c74ff",
      "updated_at": "2019-07-27T10:33+0000"
    },
    {
      "conference": "DEFCON27",
      "name": "Village",
      "id": 40005,
      "color": "#AD1457",
      "updated_at": "2019-07-27T10:33+0000"
    },
    {
      "conference": "DEFCON27",
      "name": "DemoLab",
      "id": 40006,
      "color": "#AD1457",
      "updated_at": "2019-07-27T10:33+0000"
    }
  ]
}